mb_ethereum/__init__.py
mb_ethereum/cli/__init__.py
mb_ethereum/cli/helpers.py
mb_ethereum/cli/cmd/__init__.py
mb_ethereum/cli/cmd/account_cmd.py
mb_ethereum/cli/cmd/cancel_cmd.py
mb_ethereum/cli/cmd/contract_call_cmd.py
mb_ethereum/cli/cmd/contract_signatures_cmd.py
mb_ethereum/cli/cmd/contract_tx_cmd.py
mb_ethereum/cli/cmd/convert_cmd.py
mb_ethereum/cli/cmd/decode_bytes_cmd.py
mb_ethereum/cli/cmd/decode_raw_tx_cmd.py
mb_ethereum/cli/cmd/decode_tx_input_cmd.py
mb_ethereum/cli/cmd/deploy_cmd.py
mb_ethereum/cli/cmd/encode_abi_cmd.py
mb_ethereum/cli/cmd/example_cmd.py
mb_ethereum/cli/cmd/find_address_cmd.py
mb_ethereum/cli/cmd/mnemonic_cmd.py
mb_ethereum/cli/cmd/node_cmd.py
mb_ethereum/cli/cmd/private_key_cmd.py
mb_ethereum/cli/cmd/rpc_cmd.py
mb_ethereum/cli/cmd/send_cmd.py
mb_ethereum/cli/cmd/sign_cmd.py
mb_ethereum/cli/cmd/solc_cmd.py
mb_ethereum/cli/cmd/speedup_cmd.py
mb_ethereum/cli/cmd/transfer_all_cmd.py
mb_ethereum/cli/examples/account.yml
mb_ethereum/cli/examples/cancel.yml
mb_ethereum/cli/examples/contract-call.yml
mb_ethereum/cli/examples/contract-tx.yml
mb_ethereum/cli/examples/deploy.yml
mb_ethereum/cli/examples/node.yml
mb_ethereum/cli/examples/rpc.yml
mb_ethereum/cli/examples/send.yml
mb_ethereum/cli/examples/sign.yml
mb_ethereum/cli/examples/speedup.yml
mb_ethereum/cli/examples/transfer-all.yml
mb_ethereum/datawrapper/etherscan_api.py
mb_ethereum/datawrapper/etherscan_web.py
mb_ethereum/eth/__init__.py
mb_ethereum/eth/eth_abi.py
mb_ethereum/eth/eth_account.py
mb_ethereum/eth/eth_block.py
mb_ethereum/eth/eth_erc20.py
mb_ethereum/eth/eth_rpc.py
mb_ethereum/eth/eth_tx.py
mb_ethereum/eth/eth_txpool.py
mb_ethereum/eth/eth_utils.py
mb_ethereum-0.3.0.dist-info/METADATA
mb_ethereum-0.3.0.dist-info/WHEEL
mb_ethereum-0.3.0.dist-info/entry_points.txt
mb_ethereum-0.3.0.dist-info/top_level.txt
mb_ethereum-0.3.0.dist-info/RECORD
