Metadata-Version: 2.1
Name: mb-ethereum
Version: 0.3.0
Summary: UNKNOWN
Home-page: UNKNOWN
License: UNKNOWN
Platform: UNKNOWN
Requires-Python: >=3.10
Requires-Dist: click (~=8.0.1)
Requires-Dist: click-aliases (~=1.0.1)
Requires-Dist: halo (==0.0.31)
Requires-Dist: PyYAML (~=5.4.1)
Requires-Dist: Jinja2 (~=3.0)
Requires-Dist: eth-account (==0.5.6)
Requires-Dist: websocket-client (==1.2.3)
Requires-Dist: web3 (==5.26.0)
Requires-Dist: toml (==0.10.2)
Requires-Dist: beautifulsoup4 (==4.10.0)
Requires-Dist: rlp (==2.0.1)
Requires-Dist: cachetools (==4.2.2)
Requires-Dist: mb-std (~=0.2.0)
Provides-Extra: dev
Requires-Dist: pytest (==6.2.5) ; extra == 'dev'
Requires-Dist: pytest-xdist (==2.5.0) ; extra == 'dev'
Requires-Dist: pre-commit (==2.16.0) ; extra == 'dev'
Requires-Dist: wheel (==0.37.0) ; extra == 'dev'
Requires-Dist: twine (==3.7.1) ; extra == 'dev'
Requires-Dist: pip-audit (==1.1.1) ; extra == 'dev'
